bilibili_video_download_mcp/__init__.py
bilibili_video_download_mcp/__main__.py
bilibili_video_download_mcp/server.py
bilibili_video_download_mcp/you_get/__init__.py
bilibili_video_download_mcp/you_get/common.py
bilibili_video_download_mcp/you_get/extractor.py
bilibili_video_download_mcp/you_get/json_output.py
bilibili_video_download_mcp/you_get/version.py
bilibili_video_download_mcp/you_get/extractors/__init__.py
bilibili_video_download_mcp/you_get/extractors/acfun.py
bilibili_video_download_mcp/you_get/extractors/alive.py
bilibili_video_download_mcp/you_get/extractors/archive.py
bilibili_video_download_mcp/you_get/extractors/baidu.py
bilibili_video_download_mcp/you_get/extractors/bandcamp.py
bilibili_video_download_mcp/you_get/extractors/baomihua.py
bilibili_video_download_mcp/you_get/extractors/bigthink.py
bilibili_video_download_mcp/you_get/extractors/bilibili.py
bilibili_video_download_mcp/you_get/extractors/bokecc.py
bilibili_video_download_mcp/you_get/extractors/cbs.py
bilibili_video_download_mcp/you_get/extractors/ckplayer.py
bilibili_video_download_mcp/you_get/extractors/cntv.py
bilibili_video_download_mcp/you_get/extractors/coub.py
bilibili_video_download_mcp/you_get/extractors/dailymotion.py
bilibili_video_download_mcp/you_get/extractors/douban.py
bilibili_video_download_mcp/you_get/extractors/douyin.py
bilibili_video_download_mcp/you_get/extractors/douyutv.py
bilibili_video_download_mcp/you_get/extractors/ehow.py
bilibili_video_download_mcp/you_get/extractors/embed.py
bilibili_video_download_mcp/you_get/extractors/facebook.py
bilibili_video_download_mcp/you_get/extractors/fc2video.py
bilibili_video_download_mcp/you_get/extractors/flickr.py
bilibili_video_download_mcp/you_get/extractors/freesound.py
bilibili_video_download_mcp/you_get/extractors/funshion.py
bilibili_video_download_mcp/you_get/extractors/giphy.py
bilibili_video_download_mcp/you_get/extractors/google.py
bilibili_video_download_mcp/you_get/extractors/heavymusic.py
bilibili_video_download_mcp-1.0.12.dist-info/METADATA
bilibili_video_download_mcp-1.0.12.dist-info/WHEEL
bilibili_video_download_mcp-1.0.12.dist-info/entry_points.txt
bilibili_video_download_mcp-1.0.12.dist-info/licenses/LICENSE
bilibili_video_download_mcp-1.0.12.dist-info/RECORD
