Metadata-Version: 2.4
Name: bilibili-video-download-mcp
Version: 1.0.12
Summary: Bilibili video downloader MCP server based on you-get
Author-email: Bilibili Video Download MCP <dev@example.com>
License: MIT
License-File: LICENSE
Classifier: Development Status :: 4 - Beta
Classifier: Intended Audience :: Developers
Classifier: License :: OSI Approved :: MIT License
Classifier: Programming Language :: Python :: 3
Classifier: Programming Language :: Python :: 3.10
Classifier: Programming Language :: Python :: 3.11
Classifier: Programming Language :: Python :: 3.12
Requires-Python: >=3.10
Requires-Dist: dukpy>=0.5.0
Requires-Dist: mcp>=1.0.0
Requires-Dist: requests>=2.25.0
Requires-Dist: urllib3>=1.26.0
